aws_sfn_builder/__init__.py
aws_sfn_builder/base.py
aws_sfn_builder/choice_rules.py
aws_sfn_builder/runner.py
aws_sfn_builder/states.py
aws_sfn_builder/examples/01_state_machine_from_simple_description.py
aws_sfn_builder/examples/__init__.py
tests/aws_examples/__init__.py
aws_sfn_builder-0.0.10.dist-info/LICENSE
aws_sfn_builder-0.0.10.dist-info/METADATA
aws_sfn_builder-0.0.10.dist-info/WHEEL
aws_sfn_builder-0.0.10.dist-info/top_level.txt
aws_sfn_builder-0.0.10.dist-info/RECORD
