Metadata-Version: 2.1
Name: aws-sfn-builder
Version: 0.0.10
Summary: AWS Step Functions: state machine boilerplate generator
Home-page: https://github.com/jbasko/aws-sfn-builder
Author: Jazeps Basko
Author-email: jazeps.basko@gmail.com
Maintainer: Jazeps Basko
Maintainer-email: jazeps.basko@gmail.com
License: MIT
Keywords: aws,asl,sfn,step functions,state machine,boilerplate
Platform: UNKNOWN
Classifier: Development Status :: 3 - Alpha
Classifier: Intended Audience :: Developers
Classifier: Programming Language :: Python
Classifier: Programming Language :: Python :: 3
Classifier: Programming Language :: Python :: 3.6
Classifier: Programming Language :: Python :: 3.7
Classifier: License :: OSI Approved :: MIT License
Requires-Python: >=3.6.0
Requires-Dist: bidict
Requires-Dist: dataclasses
Requires-Dist: jsonpath-ng
